fle/.example.env
fle/__init__.py
fle/__main__.py
fle/mcp_dataloader.py
fle/overlay.py
fle/overlay_mcp.py
fle/run.py
fle/server.py
fle/agents/__init__.py
fle/agents/agent_abc.py
fle/agents/gym_agent.py
fle/agents/models.py
fle/agents/data/run_trace.py
fle/agents/data/screenshots_from_run.py
fle/agents/data/blueprints_to_policies/README.md
fle/agents/data/blueprints_to_policies/__init__.py
fle/agents/data/blueprints_to_policies/blueprint_analyzer.py
fle/agents/data/blueprints_to_policies/blueprint_analyzer_with_connect.py
fle/agents/data/blueprints_to_policies/blueprint_analyzer_with_place_next_to.py
fle/agents/data/blueprints_to_policies/blueprint_metadata_generator.py
fle/agents/data/blueprints_to_policies/blueprint_refactor.py
fle/agents/data/blueprints_to_policies/factorio_school.py
fle/agents/data/blueprints_to_policies/loop_generator.py
fle/agents/data/blueprints_to_policies/parse_blueprints.py
fle/agents/data/blueprints_to_policies/processing_state.py
fle/agents/data/blueprints_to_policies/schema.json
fle/agents/data/blueprints_to_policies/test_template.jinja2
fle/agents/data/blueprints_to_policies/trajectory_generator.py
fle/agents/data/blueprints_to_policies/util.py
fle/agents/data/blueprints_to_policies/models/__init__.py
fle/agents/data/blueprints_to_policies/models/blueprint_entity.py
fle/agents/data/sprites/basis_image_resolver.py
fle/agents/data/sprites/download.py
fle/agents/data/sprites/generate_sprites.py
fle/agents/data/sprites/run.py
fle/agents/data/sprites/sample_blueprint.json
fle/agents/data/sprites/sample_blueprint.txt
fle/agents/data/sprites/upload.py
fle/agents/data/sprites/extractors/alerts.py
fle/agents/data/sprites/extractors/character.py
fle/agents/data/sprites/extractors/decoratives.py
fle/agents/data/sprites/extractors/entities.py
fle/agents/data/sprites/extractors/icons.py
fle/agents/data/sprites/extractors/resources.py
fle/agents/data/sprites/extractors/terrain.py
fle/agents/data/sprites/extractors/trees.py
factorio_learning_environment-0.3.0.dist-info/METADATA
factorio_learning_environment-0.3.0.dist-info/WHEEL
factorio_learning_environment-0.3.0.dist-info/entry_points.txt
factorio_learning_environment-0.3.0.dist-info/licenses/LICENSE
factorio_learning_environment-0.3.0.dist-info/RECORD
