Metadata-Version: 2.4
Name: factorio-learning-environment
Version: 0.3.0
Summary: Factorio Learning Environment
Project-URL: homepage, https://jackhopkins.github.io/factorio-learning-environment/
Project-URL: leaderboard, https://jackhopkins.github.io/factorio-learning-environment/leaderboard/
Author-email: Jack Hopkins <jack.hopkins@me.com>, Mart Bakler <martbakler50@gmail.com>, Neel Kant <contact@neelkant.io>, Harshit Sharma <harshsha64@gmail.com>, Kian Kyars <kiankyars@gmail.com>
License: MIT
License-File: LICENSE
Classifier: Development Status :: 4 - Beta
Classifier: Intended Audience :: Developers
Classifier: Intended Audience :: Science/Research
Classifier: License :: OSI Approved :: MIT License
Classifier: Programming Language :: Python :: 3
Classifier: Programming Language :: Python :: 3.10
Classifier: Programming Language :: Python :: 3.11
Classifier: Programming Language :: Python :: 3.12
Classifier: Programming Language :: Python :: 3.13
Classifier: Topic :: Scientific/Engineering :: Artificial Intelligence
Requires-Python: >=3.10
Requires-Dist: a2a-sdk
Requires-Dist: factorio-rcon-py==1.2.1
Requires-Dist: huggingface-hub>=0.35.3
Requires-Dist: lupa>=2.4
Requires-Dist: memoization>=0.4.0
Requires-Dist: numpy>=2.2.3
Requires-Dist: pillow>=11.1.0
Requires-Dist: platformdirs>=4.3.8
Requires-Dist: pydantic>=2.10.6
Requires-Dist: python-dotenv>=1.0.1
Requires-Dist: pyyaml>=6.0.2
Requires-Dist: slpp>=1.2.3
Requires-Dist: tenacity>=9.0.0
Provides-Extra: eval
Requires-Dist: aiohttp>=3.8.0; extra == 'eval'
Requires-Dist: anthropic>=0.49.0; extra == 'eval'
Requires-Dist: fastapi>=0.68.0; extra == 'eval'
Requires-Dist: gym; extra == 'eval'
Requires-Dist: openai>=1.66.3; extra == 'eval'
Requires-Dist: uvicorn>=0.15.0; extra == 'eval'
Provides-Extra: mcp
Requires-Dist: dulwich; extra == 'mcp'
Requires-Dist: mcp[cli]; extra == 'mcp'
Provides-Extra: psql
Requires-Dist: psycopg2>=2.9.10; extra == 'psql'
